gorse/__init__.py
gorse/gorse.py
gorse-0.4.3.dist-info/LICENSE
gorse-0.4.3.dist-info/METADATA
gorse-0.4.3.dist-info/WHEEL
gorse-0.4.3.dist-info/top_level.txt
gorse-0.4.3.dist-info/RECORD
