Metadata-Version: 2.1
Name: gorse
Version: 0.4.3
Summary: An interesting python package
Author-email: Mark Hoo <markhoo@foxmail.com>
Project-URL: Homepage, https://github.com/MarkHoo/gorse
Project-URL: Bug Tracker, https://github.com/MarkHoo/gorse/issues
Classifier: Programming Language :: Python :: 3
Classifier: License :: OSI Approved :: Apache Software License
Classifier: Operating System :: OS Independent
Classifier: Framework :: Pytest
Classifier: Programming Language :: Python :: 3.8
Classifier: Programming Language :: Python :: 3.9
Classifier: Programming Language :: Python :: 3.10
Classifier: Programming Language :: Python :: 3.11
Requires-Python: >=3.8
License-File: LICENSE
